[{"IndexCode":"COMPOSITE","PrevVal":6994.395,"HighVal":6996.24,"LowVal":6938.421,"LastVal":6951.276,"ChgVal":-43.12,"ChgPct":-0.62,"DtCreate":"2022-10-11T14:50:00","Links":[{"Rel":"self","Href":"/api/api/marketsummary/indexsummary/COMPOSITE","Method":"GET"}]},{"IndexCode":"DBX","PrevVal":1872.062,"HighVal":1877.461,"LowVal":1837.582,"LastVal":1843.023,"ChgVal":-29.04,"ChgPct":-1.55,"DtCreate":"2022-10-11T14:50:00","Links":[{"Rel":"self","Href":"/api/api/marketsummary/indexsummary/DBX","Method":"GET"}]},{"IndexCode":"MBX","PrevVal":1858.41,"HighVal":1860.767,"LowVal":1850.992,"LastVal":1856.065,"ChgVal":-2.35,"ChgPct":-0.13,"DtCreate":"2022-10-11T14:49:59","Links":[{"Rel":"self","Href":"/api/api/marketsummary/indexsummary/MBX","Method":"GET"}]},{"IndexCode":"KOMPAS100","PrevVal":1244.407,"HighVal":1245.01,"LowVal":1234.607,"LastVal":1236.887,"ChgVal":-7.52,"ChgPct":-0.6,"DtCreate":"2022-10-11T14:50:00","Links":[{"Rel":"self","Href":"/api/api/marketsummary/indexsummary/KOMPAS100","Method":"GET"}]},{"IndexCode":"INFOBANK15","PrevVal":1138.167,"HighVal":1139.616,"LowVal":1127.898,"LastVal":1129.863,"ChgVal":-8.3,"ChgPct":-0.73,"DtCreate":"2022-10-11T14:50:00","Links":[{"Rel":"self","Href":"/api/api/marketsummary/indexsummary/INFOBANK15","Method":"GET"}]},{"IndexCode":"LQ45","PrevVal":996.686,"HighVal":996.924,"LowVal":988.337,"LastVal":990.415,"ChgVal":-6.27,"ChgPct":-0.63,"DtCreate":"2022-10-11T14:50:00","Links":[{"Rel":"self","Href":"/api/api/marketsummary/indexsummary/LQ45","Method":"GET"}]},{"IndexCode":"JII","PrevVal":610.129,"HighVal":612.01,"LowVal":607.504,"LastVal":609.586,"ChgVal":-0.54,"ChgPct":-0.09,"DtCreate":"2022-10-11T14:50:00","Links":[{"Rel":"self","Href":"/api/api/marketsummary/indexsummary/JII","Method":"GET"}]},{"IndexCode":"BISNIS-27","PrevVal":585.867,"HighVal":586.388,"LowVal":582.356,"LastVal":584.684,"ChgVal":-1.18,"ChgPct":-0.2,"DtCreate":"2022-10-11T14:49:59","Links":[{"Rel":"self","Href":"/api/api/marketsummary/indexsummary/BISNIS-27","Method":"GET"}]},{"IndexCode":"IDXHIDIV20","PrevVal":559.902,"HighVal":560.564,"LowVal":556.904,"LastVal":559.418,"ChgVal":-0.48,"ChgPct":-0.09,"DtCreate":"2022-10-11T14:49:58","Links":[{"Rel":"self","Href":"/api/api/marketsummary/indexsummary/IDXHIDIV20","Method":"GET"}]},{"IndexCode":"IDX30","PrevVal":526.458,"HighVal":526.458,"LowVal":521.49,"LastVal":522.694,"ChgVal":-3.76,"ChgPct":-0.72,"DtCreate":"2022-10-11T14:50:00","Links":[{"Rel":"self","Href":"/api/api/marketsummary/indexsummary/IDX30","Method":"GET"}]},{"IndexCode":"Investor33","PrevVal":488.125,"HighVal":488.646,"LowVal":485.064,"LastVal":487.557,"ChgVal":-0.57,"ChgPct":-0.12,"DtCreate":"2022-10-11T14:50:00","Links":[{"Rel":"self","Href":"/api/api/marketsummary/indexsummary/Investor33","Method":"GET"}]},{"IndexCode":"SRI-KEHATI","PrevVal":417.253,"HighVal":417.966,"LowVal":414.437,"LastVal":416.839,"ChgVal":-0.41,"ChgPct":-0.1,"DtCreate":"2022-10-11T14:50:00","Links":[{"Rel":"self","Href":"/api/api/marketsummary/indexsummary/SRI-KEHATI","Method":"GET"}]},{"IndexCode":"IDXBUMN20","PrevVal":407.709,"HighVal":408.393,"LowVal":405.09,"LastVal":407.382,"ChgVal":-0.33,"ChgPct":-0.08,"DtCreate":"2022-10-11T14:50:00","Links":[{"Rel":"self","Href":"/api/api/marketsummary/indexsummary/IDXBUMN20","Method":"GET"}]},{"IndexCode":"IDXSMC-LIQ","PrevVal":374.345,"HighVal":376.492,"LowVal":373.929,"LastVal":375.43,"ChgVal":1.09,"ChgPct":0.29,"DtCreate":"2022-10-11T14:50:00","Links":[{"Rel":"self","Href":"/api/api/marketsummary/indexsummary/IDXSMC-LIQ","Method":"GET"}]},{"IndexCode":"IDXSMC-COM","PrevVal":366.346,"HighVal":367.6,"LowVal":364.367,"LastVal":365.027,"ChgVal":-1.32,"ChgPct":-0.36,"DtCreate":"2022-10-11T14:50:00","Links":[{"Rel":"self","Href":"/api/api/marketsummary/indexsummary/IDXSMC-COM","Method":"GET"}]},{"IndexCode":"MNC36","PrevVal":353.728,"HighVal":354.022,"LowVal":351.605,"LastVal":353.077,"ChgVal":-0.65,"ChgPct":-0.18,"DtCreate":"2022-10-11T14:50:00","Links":[{"Rel":"self","Href":"/api/api/marketsummary/indexsummary/MNC36","Method":"GET"}]},{"IndexCode":"SMInfra18","PrevVal":334.491,"HighVal":334.623,"LowVal":332.01,"LastVal":334.061,"ChgVal":-0.43,"ChgPct":-0.13,"DtCreate":"2022-10-11T14:50:00","Links":[{"Rel":"self","Href":"/api/api/marketsummary/indexsummary/SMInfra18","Method":"GET"}]},{"IndexCode":"PEFINDO25","PrevVal":281.555,"HighVal":282.919,"LowVal":274.27,"LastVal":274.822,"ChgVal":-6.73,"ChgPct":-2.39,"DtCreate":"2022-10-11T14:50:00","Links":[{"Rel":"self","Href":"/api/api/marketsummary/indexsummary/PEFINDO25","Method":"GET"}]},{"IndexCode":"JII70","PrevVal":205.994,"HighVal":206.676,"LowVal":205.255,"LastVal":205.993,"ChgVal":0,"ChgPct":0,"DtCreate":"2022-10-11T14:49:59","Links":[{"Rel":"self","Href":"/api/api/marketsummary/indexsummary/JII70","Method":"GET"}]},{"IndexCode":"ISSI","PrevVal":204.597,"HighVal":204.809,"LowVal":203.806,"LastVal":204.243,"ChgVal":-0.35,"ChgPct":-0.17,"DtCreate":"2022-10-11T14:50:00","Links":[{"Rel":"self","Href":"/api/api/marketsummary/indexsummary/ISSI","Method":"GET"}]},{"IndexCode":"I-GRADE","PrevVal":201.377,"HighVal":201.582,"LowVal":199.84,"LastVal":200.966,"ChgVal":-0.41,"ChgPct":-0.2,"DtCreate":"2022-10-11T14:50:00","Links":[{"Rel":"self","Href":"/api/api/marketsummary/indexsummary/I-GRADE","Method":"GET"}]},{"IndexCode":"IDXQ30","PrevVal":164.516,"HighVal":164.557,"LowVal":163.473,"LastVal":163.903,"ChgVal":-0.61,"ChgPct":-0.37,"DtCreate":"2022-10-11T14:49:59","Links":[{"Rel":"self","Href":"/api/api/marketsummary/indexsummary/IDXQ30","Method":"GET"}]},{"IndexCode":"IDXV30","PrevVal":156.472,"HighVal":156.964,"LowVal":155.894,"LastVal":156.21,"ChgVal":-0.26,"ChgPct":-0.17,"DtCreate":"2022-10-11T14:49:59","Links":[{"Rel":"self","Href":"/api/api/marketsummary/indexsummary/IDXV30","Method":"GET"}]},{"IndexCode":"IDXG30","PrevVal":156.203,"HighVal":156.039,"LowVal":155.155,"LastVal":155.529,"ChgVal":-0.67,"ChgPct":-0.43,"DtCreate":"2022-10-11T14:49:59","Links":[{"Rel":"self","Href":"/api/api/marketsummary/indexsummary/IDXG30","Method":"GET"}]},{"IndexCode":"IDXESGL","PrevVal":143.507,"HighVal":143.556,"LowVal":142.572,"LastVal":143.197,"ChgVal":-0.31,"ChgPct":-0.22,"DtCreate":"2022-10-11T14:50:00","Links":[{"Rel":"self","Href":"/api/api/marketsummary/indexsummary/IDXESGL","Method":"GET"}]},{"IndexCode":"IDX80","PrevVal":140.234,"HighVal":140.333,"LowVal":139.163,"LastVal":139.42,"ChgVal":-0.81,"ChgPct":-0.58,"DtCreate":"2022-10-11T14:50:00","Links":[{"Rel":"self","Href":"/api/api/marketsummary/indexsummary/IDX80","Method":"GET"}]},{"IndexCode":"ESGSKEHATI","PrevVal":136.186,"HighVal":136.383,"LowVal":135.345,"LastVal":136.053,"ChgVal":-0.13,"ChgPct":-0.1,"DtCreate":"2022-10-11T14:50:00","Links":[{"Rel":"self","Href":"/api/api/marketsummary/indexsummary/ESGSKEHATI","Method":"GET"}]},{"IndexCode":"ESGQKEHATI","PrevVal":135.699,"HighVal":135.797,"LowVal":134.797,"LastVal":135.455,"ChgVal":-0.24,"ChgPct":-0.18,"DtCreate":"2022-10-11T14:50:00","Links":[{"Rel":"self","Href":"/api/api/marketsummary/indexsummary/ESGQKEHATI","Method":"GET"}]},{"IndexCode":"IDXMESBUMN","PrevVal":100.748,"HighVal":101.123,"LowVal":100.005,"LastVal":100.891,"ChgVal":0.14,"ChgPct":0.14,"DtCreate":"2022-10-11T14:49:59","Links":[{"Rel":"self","Href":"/api/api/marketsummary/indexsummary/IDXMESBUMN","Method":"GET"}]}]