[{"IntRow":1,"IndexCode":"IDXENERGY","PrevVal":2008.108,"HighVal":2032.235,"LowVal":2006.05,"LastVal":2013.192,"ChgVal":5.08,"ChgPct":0.25,"DTCreate":"2022-11-02T15:15:00"},{"IntRow":2,"IndexCode":"IDXBASIC","PrevVal":1271.877,"HighVal":1288.504,"LowVal":1271.877,"LastVal":1282.844,"ChgVal":10.97,"ChgPct":0.86,"DTCreate":"2022-11-02T15:15:00"},{"IntRow":3,"IndexCode":"IDXINDUST","PrevVal":1258.814,"HighVal":1259.723,"LowVal":1233.122,"LastVal":1241.374,"ChgVal":-17.44,"ChgPct":-1.39,"DTCreate":"2022-11-02T15:14:45"},{"IntRow":4,"IndexCode":"IDXNONCYC","PrevVal":732.121,"HighVal":732.537,"LowVal":725.25,"LastVal":729.369,"ChgVal":-2.75,"ChgPct":-0.38,"DTCreate":"2022-11-02T15:14:59"},{"IntRow":5,"IndexCode":"IDXCYCLIC","PrevVal":876.244,"HighVal":885.245,"LowVal":876.153,"LastVal":884.635,"ChgVal":8.39,"ChgPct":0.96,"DTCreate":"2022-11-02T15:14:59"},{"IntRow":6,"IndexCode":"IDXHEALTH","PrevVal":1497.055,"HighVal":1503.182,"LowVal":1482.646,"LastVal":1492.589,"ChgVal":-4.47,"ChgPct":-0.3,"DTCreate":"2022-11-02T15:14:51"},{"IntRow":7,"IndexCode":"IDXFINANCE","PrevVal":1484.241,"HighVal":1486.746,"LowVal":1470.552,"LastVal":1475.889,"ChgVal":-8.35,"ChgPct":-0.56,"DTCreate":"2022-11-02T15:14:57"},{"IntRow":8,"IndexCode":"IDXPROPERT","PrevVal":693.399,"HighVal":695.469,"LowVal":688.466,"LastVal":692.572,"ChgVal":-0.83,"ChgPct":-0.12,"DTCreate":"2022-11-02T15:15:00"},{"IntRow":9,"IndexCode":"IDXTECHNO","PrevVal":6483.152,"HighVal":6631.608,"LowVal":6483.152,"LastVal":6602.786,"ChgVal":119.63,"ChgPct":1.85,"DTCreate":"2022-11-02T15:14:56"},{"IntRow":10,"IndexCode":"IDXINFRA","PrevVal":935.643,"HighVal":938.222,"LowVal":925.689,"LastVal":931.744,"ChgVal":-3.9,"ChgPct":-0.42,"DTCreate":"2022-11-02T15:14:53"},{"IntRow":11,"IndexCode":"IDXTRANS","PrevVal":1823.85,"HighVal":1823.859,"LowVal":1804.587,"LastVal":1815.899,"ChgVal":-7.95,"ChgPct":-0.44,"DTCreate":"2022-11-02T15:14:53"}]