[{"IndexCode":"COMPOSITE","PrevVal":7168.87,"HighVal":7168.87,"LowVal":7168.87,"LastVal":7168.87,"ChgVal":0,"ChgPct":0,"DtCreate":"2022-09-19T04:06:03","Links":[{"Rel":"self","Href":"/api/api/marketsummary/indexsummary/COMPOSITE","Method":"GET"}]},{"IndexCode":"DBX","PrevVal":1965.232,"HighVal":1965.232,"LowVal":1965.232,"LastVal":1965.232,"ChgVal":0,"ChgPct":0,"DtCreate":"2022-09-19T04:06:03","Links":[{"Rel":"self","Href":"/api/api/marketsummary/indexsummary/DBX","Method":"GET"}]},{"IndexCode":"MBX","PrevVal":1898.682,"HighVal":1898.682,"LowVal":1898.682,"LastVal":1898.682,"ChgVal":0,"ChgPct":0,"DtCreate":"2022-09-19T04:06:03","Links":[{"Rel":"self","Href":"/api/api/marketsummary/indexsummary/MBX","Method":"GET"}]},{"IndexCode":"KOMPAS100","PrevVal":1276.801,"HighVal":1276.801,"LowVal":1276.801,"LastVal":1276.801,"ChgVal":0,"ChgPct":0,"DtCreate":"2022-09-19T04:06:03","Links":[{"Rel":"self","Href":"/api/api/marketsummary/indexsummary/KOMPAS100","Method":"GET"}]},{"IndexCode":"LQ45","PrevVal":1016.006,"HighVal":1016.006,"LowVal":1016.006,"LastVal":1016.006,"ChgVal":0,"ChgPct":0,"DtCreate":"2022-09-19T04:06:03","Links":[{"Rel":"self","Href":"/api/api/marketsummary/indexsummary/LQ45","Method":"GET"}]},{"IndexCode":"JII","PrevVal":625.374,"HighVal":625.374,"LowVal":625.374,"LastVal":625.374,"ChgVal":0,"ChgPct":0,"DtCreate":"2022-09-19T04:06:03","Links":[{"Rel":"self","Href":"/api/api/marketsummary/indexsummary/JII","Method":"GET"}]},{"IndexCode":"BISNIS-27","PrevVal":596.187,"HighVal":596.187,"LowVal":596.187,"LastVal":596.187,"ChgVal":0,"ChgPct":0,"DtCreate":"2022-09-19T04:06:03","Links":[{"Rel":"self","Href":"/api/api/marketsummary/indexsummary/BISNIS-27","Method":"GET"}]},{"IndexCode":"IDXHIDIV20","PrevVal":568.455,"HighVal":568.455,"LowVal":568.455,"LastVal":568.455,"ChgVal":0,"ChgPct":0,"DtCreate":"2022-09-19T04:06:03","Links":[{"Rel":"self","Href":"/api/api/marketsummary/indexsummary/IDXHIDIV20","Method":"GET"}]},{"IndexCode":"IDX30","PrevVal":537.495,"HighVal":537.495,"LowVal":537.495,"LastVal":537.495,"ChgVal":0,"ChgPct":0,"DtCreate":"2022-09-19T04:06:03","Links":[{"Rel":"self","Href":"/api/api/marketsummary/indexsummary/IDX30","Method":"GET"}]},{"IndexCode":"Investor33","PrevVal":496.921,"HighVal":496.921,"LowVal":496.921,"LastVal":496.921,"ChgVal":0,"ChgPct":0,"DtCreate":"2022-09-19T04:06:03","Links":[{"Rel":"self","Href":"/api/api/marketsummary/indexsummary/Investor33","Method":"GET"}]},{"IndexCode":"SRI-KEHATI","PrevVal":424.302,"HighVal":424.302,"LowVal":424.302,"LastVal":424.302,"ChgVal":0,"ChgPct":0,"DtCreate":"2022-09-19T04:06:03","Links":[{"Rel":"self","Href":"/api/api/marketsummary/indexsummary/SRI-KEHATI","Method":"GET"}]},{"IndexCode":"IDXBUMN20","PrevVal":415.751,"HighVal":415.751,"LowVal":415.751,"LastVal":415.751,"ChgVal":0,"ChgPct":0,"DtCreate":"2022-09-19T04:06:03","Links":[{"Rel":"self","Href":"/api/api/marketsummary/indexsummary/IDXBUMN20","Method":"GET"}]},{"IndexCode":"IDXSMC-LIQ","PrevVal":386.509,"HighVal":386.509,"LowVal":386.509,"LastVal":386.509,"ChgVal":0,"ChgPct":0,"DtCreate":"2022-09-19T04:06:03","Links":[{"Rel":"self","Href":"/api/api/marketsummary/indexsummary/IDXSMC-LIQ","Method":"GET"}]},{"IndexCode":"IDXSMC-COM","PrevVal":383.063,"HighVal":383.063,"LowVal":383.063,"LastVal":383.063,"ChgVal":0,"ChgPct":0,"DtCreate":"2022-09-19T04:06:03","Links":[{"Rel":"self","Href":"/api/api/marketsummary/indexsummary/IDXSMC-COM","Method":"GET"}]},{"IndexCode":"MNC36","PrevVal":360.844,"HighVal":360.844,"LowVal":360.844,"LastVal":360.844,"ChgVal":0,"ChgPct":0,"DtCreate":"2022-09-19T04:06:03","Links":[{"Rel":"self","Href":"/api/api/marketsummary/indexsummary/MNC36","Method":"GET"}]},{"IndexCode":"SMInfra18","PrevVal":340.209,"HighVal":340.209,"LowVal":340.209,"LastVal":340.209,"ChgVal":0,"ChgPct":0,"DtCreate":"2022-09-19T04:06:03","Links":[{"Rel":"self","Href":"/api/api/marketsummary/indexsummary/SMInfra18","Method":"GET"}]},{"IndexCode":"PEFINDO25","PrevVal":301.161,"HighVal":301.161,"LowVal":301.161,"LastVal":301.161,"ChgVal":0,"ChgPct":0,"DtCreate":"2022-09-19T04:06:03","Links":[{"Rel":"self","Href":"/api/api/marketsummary/indexsummary/PEFINDO25","Method":"GET"}]},{"IndexCode":"JII70","PrevVal":212.23,"HighVal":212.23,"LowVal":212.23,"LastVal":212.23,"ChgVal":0,"ChgPct":0,"DtCreate":"2022-09-19T04:06:03","Links":[{"Rel":"self","Href":"/api/api/marketsummary/indexsummary/JII70","Method":"GET"}]},{"IndexCode":"ISSI","PrevVal":211.127,"HighVal":211.127,"LowVal":211.127,"LastVal":211.127,"ChgVal":0,"ChgPct":0,"DtCreate":"2022-09-19T04:06:03","Links":[{"Rel":"self","Href":"/api/api/marketsummary/indexsummary/ISSI","Method":"GET"}]},{"IndexCode":"I-GRADE","PrevVal":204.09,"HighVal":204.09,"LowVal":204.09,"LastVal":204.09,"ChgVal":0,"ChgPct":0,"DtCreate":"2022-09-19T04:06:03","Links":[{"Rel":"self","Href":"/api/api/marketsummary/indexsummary/I-GRADE","Method":"GET"}]},{"IndexCode":"IDXQ30","PrevVal":167.008,"HighVal":167.008,"LowVal":167.008,"LastVal":167.008,"ChgVal":0,"ChgPct":0,"DtCreate":"2022-09-19T04:06:03","Links":[{"Rel":"self","Href":"/api/api/marketsummary/indexsummary/IDXQ30","Method":"GET"}]},{"IndexCode":"IDXV30","PrevVal":161.334,"HighVal":161.334,"LowVal":161.334,"LastVal":161.334,"ChgVal":0,"ChgPct":0,"DtCreate":"2022-09-19T04:06:03","Links":[{"Rel":"self","Href":"/api/api/marketsummary/indexsummary/IDXV30","Method":"GET"}]},{"IndexCode":"IDXESGL","PrevVal":146.215,"HighVal":146.215,"LowVal":146.215,"LastVal":146.215,"ChgVal":0,"ChgPct":0,"DtCreate":"2022-09-19T04:06:03","Links":[{"Rel":"self","Href":"/api/api/marketsummary/indexsummary/IDXESGL","Method":"GET"}]},{"IndexCode":"IDX80","PrevVal":143.678,"HighVal":143.678,"LowVal":143.678,"LastVal":143.678,"ChgVal":0,"ChgPct":0,"DtCreate":"2022-09-19T04:06:03","Links":[{"Rel":"self","Href":"/api/api/marketsummary/indexsummary/IDX80","Method":"GET"}]},{"IndexCode":"ESGSKEHATI","PrevVal":138.666,"HighVal":138.666,"LowVal":138.666,"LastVal":138.666,"ChgVal":0,"ChgPct":0,"DtCreate":"2022-09-19T04:06:03","Links":[{"Rel":"self","Href":"/api/api/marketsummary/indexsummary/ESGSKEHATI","Method":"GET"}]},{"IndexCode":"ESGQKEHATI","PrevVal":137.987,"HighVal":137.987,"LowVal":137.987,"LastVal":137.987,"ChgVal":0,"ChgPct":0,"DtCreate":"2022-09-19T04:06:03","Links":[{"Rel":"self","Href":"/api/api/marketsummary/indexsummary/ESGQKEHATI","Method":"GET"}]},{"IndexCode":"IDXMESBUMN","PrevVal":103.002,"HighVal":103.002,"LowVal":103.002,"LastVal":103.002,"ChgVal":0,"ChgPct":0,"DtCreate":"2022-09-19T04:06:03","Links":[{"Rel":"self","Href":"/api/api/marketsummary/indexsummary/IDXMESBUMN","Method":"GET"}]}]