[{"IntRow":1,"IndexCode":"IDXENERGY","PrevVal":1806.223,"HighVal":1814.513,"LowVal":1795.212,"LastVal":1798.031,"ChgVal":-8.19,"ChgPct":-0.45,"DTCreate":"2022-08-16T09:57:00"},{"IntRow":2,"IndexCode":"IDXBASIC","PrevVal":1334.444,"HighVal":1340.951,"LowVal":1319.005,"LastVal":1319.219,"ChgVal":-15.23,"ChgPct":-1.14,"DTCreate":"2022-08-16T09:57:01"},{"IntRow":3,"IndexCode":"IDXINDUST","PrevVal":1313.362,"HighVal":1322.586,"LowVal":1313.362,"LastVal":1320.025,"ChgVal":6.66,"ChgPct":0.51,"DTCreate":"2022-08-16T09:57:00"},{"IntRow":4,"IndexCode":"IDXNONCYC","PrevVal":700.397,"HighVal":703.893,"LowVal":700.211,"LastVal":701.367,"ChgVal":0.97,"ChgPct":0.14,"DTCreate":"2022-08-16T09:57:01"},{"IntRow":5,"IndexCode":"IDXCYCLIC","PrevVal":892.345,"HighVal":897.887,"LowVal":891.897,"LastVal":894.749,"ChgVal":2.4,"ChgPct":0.27,"DTCreate":"2022-08-16T09:57:00"},{"IntRow":6,"IndexCode":"IDXHEALTH","PrevVal":1407.709,"HighVal":1420.62,"LowVal":1407.709,"LastVal":1413.08,"ChgVal":5.37,"ChgPct":0.38,"DTCreate":"2022-08-16T09:57:01"},{"IntRow":7,"IndexCode":"IDXFINANCE","PrevVal":1517.17,"HighVal":1523.499,"LowVal":1516.278,"LastVal":1517.448,"ChgVal":0.28,"ChgPct":0.02,"DTCreate":"2022-08-16T09:57:01"},{"IntRow":8,"IndexCode":"IDXPROPERT","PrevVal":720.75,"HighVal":726.298,"LowVal":720.75,"LastVal":723.371,"ChgVal":2.62,"ChgPct":0.36,"DTCreate":"2022-08-16T09:57:00"},{"IntRow":9,"IndexCode":"IDXTECHNO","PrevVal":7963.696,"HighVal":8112.597,"LowVal":7954.102,"LastVal":8015.474,"ChgVal":51.78,"ChgPct":0.65,"DTCreate":"2022-08-16T09:57:00"},{"IntRow":10,"IndexCode":"IDXINFRA","PrevVal":1057.048,"HighVal":1062.175,"LowVal":1052.153,"LastVal":1052.153,"ChgVal":-4.9,"ChgPct":-0.46,"DTCreate":"2022-08-16T09:57:01"},{"IntRow":11,"IndexCode":"IDXTRANS","PrevVal":2072.225,"HighVal":2083.646,"LowVal":2064.324,"LastVal":2075.444,"ChgVal":3.22,"ChgPct":0.16,"DTCreate":"2022-08-16T09:57:01"}]