[{"IntRow":1,"IndexCode":"IDXENERGY","PrevVal":1972.864,"HighVal":1975.436,"LowVal":1953.165,"LastVal":1955.666,"ChgVal":-17.2,"ChgPct":-0.87,"DTCreate":"2022-10-19T14:40:31"},{"IntRow":2,"IndexCode":"IDXBASIC","PrevVal":1228.637,"HighVal":1245.691,"LowVal":1225.259,"LastVal":1241.46,"ChgVal":12.82,"ChgPct":1.04,"DTCreate":"2022-10-19T14:40:32"},{"IntRow":3,"IndexCode":"IDXINDUST","PrevVal":1246.827,"HighVal":1259.123,"LowVal":1242.051,"LastVal":1248.675,"ChgVal":1.85,"ChgPct":0.15,"DTCreate":"2022-10-19T14:40:32"},{"IntRow":4,"IndexCode":"IDXNONCYC","PrevVal":709.633,"HighVal":718.286,"LowVal":707.048,"LastVal":717.037,"ChgVal":7.4,"ChgPct":1.04,"DTCreate":"2022-10-19T14:40:32"},{"IntRow":5,"IndexCode":"IDXCYCLIC","PrevVal":835.941,"HighVal":842.658,"LowVal":832.784,"LastVal":841.499,"ChgVal":5.56,"ChgPct":0.67,"DTCreate":"2022-10-19T14:40:32"},{"IntRow":6,"IndexCode":"IDXHEALTH","PrevVal":1456.134,"HighVal":1462.437,"LowVal":1445.735,"LastVal":1459.682,"ChgVal":3.55,"ChgPct":0.24,"DTCreate":"2022-10-19T14:40:32"},{"IntRow":7,"IndexCode":"IDXFINANCE","PrevVal":1431.357,"HighVal":1458.431,"LowVal":1427.871,"LastVal":1451.252,"ChgVal":19.9,"ChgPct":1.39,"DTCreate":"2022-10-19T14:40:32"},{"IntRow":8,"IndexCode":"IDXPROPERT","PrevVal":675.632,"HighVal":678.613,"LowVal":674.196,"LastVal":676.886,"ChgVal":1.25,"ChgPct":0.19,"DTCreate":"2022-10-19T14:40:32"},{"IntRow":9,"IndexCode":"IDXTECHNO","PrevVal":6453.604,"HighVal":6496.638,"LowVal":6408.76,"LastVal":6470.016,"ChgVal":16.41,"ChgPct":0.25,"DTCreate":"2022-10-19T14:40:32"},{"IntRow":10,"IndexCode":"IDXINFRA","PrevVal":919.861,"HighVal":929.147,"LowVal":912.667,"LastVal":923.236,"ChgVal":3.38,"ChgPct":0.37,"DTCreate":"2022-10-19T14:40:32"},{"IntRow":11,"IndexCode":"IDXTRANS","PrevVal":1752.249,"HighVal":1766.202,"LowVal":1738.788,"LastVal":1758.982,"ChgVal":6.73,"ChgPct":0.38,"DTCreate":"2022-10-19T14:40:30"}]