[{"IntRow":1,"IndexCode":"IDXENERGY","PrevVal":2017.02,"HighVal":2041.711,"LowVal":2017.02,"LastVal":2035.826,"ChgVal":18.81,"ChgPct":0.93,"DTCreate":"2022-10-24T13:58:02"},{"IntRow":2,"IndexCode":"IDXBASIC","PrevVal":1247.355,"HighVal":1258.856,"LowVal":1247.355,"LastVal":1250.19,"ChgVal":2.84,"ChgPct":0.23,"DTCreate":"2022-10-24T13:58:02"},{"IntRow":3,"IndexCode":"IDXINDUST","PrevVal":1263.145,"HighVal":1286.897,"LowVal":1263.145,"LastVal":1280.861,"ChgVal":17.72,"ChgPct":1.4,"DTCreate":"2022-10-24T13:58:02"},{"IntRow":4,"IndexCode":"IDXNONCYC","PrevVal":732.552,"HighVal":737.265,"LowVal":732.552,"LastVal":736.023,"ChgVal":3.47,"ChgPct":0.47,"DTCreate":"2022-10-24T13:58:02"},{"IntRow":5,"IndexCode":"IDXCYCLIC","PrevVal":853.63,"HighVal":863.126,"LowVal":853.63,"LastVal":858.331,"ChgVal":4.7,"ChgPct":0.55,"DTCreate":"2022-10-24T13:58:02"},{"IntRow":6,"IndexCode":"IDXHEALTH","PrevVal":1477.127,"HighVal":1503.881,"LowVal":1477.127,"LastVal":1503.811,"ChgVal":26.68,"ChgPct":1.81,"DTCreate":"2022-10-24T13:58:01"},{"IntRow":7,"IndexCode":"IDXFINANCE","PrevVal":1490.55,"HighVal":1513.892,"LowVal":1490.55,"LastVal":1506.607,"ChgVal":16.06,"ChgPct":1.08,"DTCreate":"2022-10-24T13:58:02"},{"IntRow":8,"IndexCode":"IDXPROPERT","PrevVal":681.493,"HighVal":685.52,"LowVal":681.493,"LastVal":682.951,"ChgVal":1.46,"ChgPct":0.21,"DTCreate":"2022-10-24T13:58:02"},{"IntRow":9,"IndexCode":"IDXTECHNO","PrevVal":6474.002,"HighVal":6560.665,"LowVal":6433.787,"LastVal":6440.281,"ChgVal":-33.72,"ChgPct":-0.52,"DTCreate":"2022-10-24T13:58:02"},{"IntRow":10,"IndexCode":"IDXINFRA","PrevVal":944.145,"HighVal":951,"LowVal":941.45,"LastVal":943.015,"ChgVal":-1.13,"ChgPct":-0.12,"DTCreate":"2022-10-24T13:58:02"},{"IntRow":11,"IndexCode":"IDXTRANS","PrevVal":1778.176,"HighVal":1827.169,"LowVal":1778.176,"LastVal":1784.182,"ChgVal":6.01,"ChgPct":0.34,"DTCreate":"2022-10-24T13:58:02"}]