[{"IndexCode":"COMPOSITE","PrevVal":7026.783,"HighVal":7026.783,"LowVal":7026.783,"LastVal":7026.783,"ChgVal":0,"ChgPct":0,"DtCreate":"2022-10-10T04:05:50","Links":[{"Rel":"self","Href":"/api/api/marketsummary/indexsummary/COMPOSITE","Method":"GET"}]},{"IndexCode":"DBX","PrevVal":1901.684,"HighVal":1901.684,"LowVal":1901.684,"LastVal":1901.684,"ChgVal":0,"ChgPct":0,"DtCreate":"2022-10-10T04:05:50","Links":[{"Rel":"self","Href":"/api/api/marketsummary/indexsummary/DBX","Method":"GET"}]},{"IndexCode":"MBX","PrevVal":1863.577,"HighVal":1863.577,"LowVal":1863.577,"LastVal":1863.577,"ChgVal":0,"ChgPct":0,"DtCreate":"2022-10-10T04:05:50","Links":[{"Rel":"self","Href":"/api/api/marketsummary/indexsummary/MBX","Method":"GET"}]},{"IndexCode":"KOMPAS100","PrevVal":1249.141,"HighVal":1249.141,"LowVal":1249.141,"LastVal":1249.141,"ChgVal":0,"ChgPct":0,"DtCreate":"2022-10-10T04:05:50","Links":[{"Rel":"self","Href":"/api/api/marketsummary/indexsummary/KOMPAS100","Method":"GET"}]},{"IndexCode":"LQ45","PrevVal":999.391,"HighVal":999.391,"LowVal":999.391,"LastVal":999.391,"ChgVal":0,"ChgPct":0,"DtCreate":"2022-10-10T04:05:50","Links":[{"Rel":"self","Href":"/api/api/marketsummary/indexsummary/LQ45","Method":"GET"}]},{"IndexCode":"JII","PrevVal":613.707,"HighVal":613.707,"LowVal":613.707,"LastVal":613.707,"ChgVal":0,"ChgPct":0,"DtCreate":"2022-10-10T04:05:50","Links":[{"Rel":"self","Href":"/api/api/marketsummary/indexsummary/JII","Method":"GET"}]},{"IndexCode":"BISNIS-27","PrevVal":586.959,"HighVal":586.959,"LowVal":586.959,"LastVal":586.959,"ChgVal":0,"ChgPct":0,"DtCreate":"2022-10-10T04:05:50","Links":[{"Rel":"self","Href":"/api/api/marketsummary/indexsummary/BISNIS-27","Method":"GET"}]},{"IndexCode":"IDXHIDIV20","PrevVal":562.994,"HighVal":562.994,"LowVal":562.994,"LastVal":562.994,"ChgVal":0,"ChgPct":0,"DtCreate":"2022-10-10T04:05:50","Links":[{"Rel":"self","Href":"/api/api/marketsummary/indexsummary/IDXHIDIV20","Method":"GET"}]},{"IndexCode":"IDX30","PrevVal":528.301,"HighVal":528.301,"LowVal":528.301,"LastVal":528.301,"ChgVal":0,"ChgPct":0,"DtCreate":"2022-10-10T04:05:50","Links":[{"Rel":"self","Href":"/api/api/marketsummary/indexsummary/IDX30","Method":"GET"}]},{"IndexCode":"Investor33","PrevVal":489.603,"HighVal":489.603,"LowVal":489.603,"LastVal":489.603,"ChgVal":0,"ChgPct":0,"DtCreate":"2022-10-10T04:05:50","Links":[{"Rel":"self","Href":"/api/api/marketsummary/indexsummary/Investor33","Method":"GET"}]},{"IndexCode":"SRI-KEHATI","PrevVal":416.859,"HighVal":416.859,"LowVal":416.859,"LastVal":416.859,"ChgVal":0,"ChgPct":0,"DtCreate":"2022-10-10T04:05:50","Links":[{"Rel":"self","Href":"/api/api/marketsummary/indexsummary/SRI-KEHATI","Method":"GET"}]},{"IndexCode":"IDXBUMN20","PrevVal":408.856,"HighVal":408.856,"LowVal":408.856,"LastVal":408.856,"ChgVal":0,"ChgPct":0,"DtCreate":"2022-10-10T04:05:50","Links":[{"Rel":"self","Href":"/api/api/marketsummary/indexsummary/IDXBUMN20","Method":"GET"}]},{"IndexCode":"IDXSMC-LIQ","PrevVal":376.325,"HighVal":376.325,"LowVal":376.325,"LastVal":376.325,"ChgVal":0,"ChgPct":0,"DtCreate":"2022-10-10T04:05:50","Links":[{"Rel":"self","Href":"/api/api/marketsummary/indexsummary/IDXSMC-LIQ","Method":"GET"}]},{"IndexCode":"IDXSMC-COM","PrevVal":369.691,"HighVal":369.691,"LowVal":369.691,"LastVal":369.691,"ChgVal":0,"ChgPct":0,"DtCreate":"2022-10-10T04:05:50","Links":[{"Rel":"self","Href":"/api/api/marketsummary/indexsummary/IDXSMC-COM","Method":"GET"}]},{"IndexCode":"MNC36","PrevVal":354.995,"HighVal":354.995,"LowVal":354.995,"LastVal":354.995,"ChgVal":0,"ChgPct":0,"DtCreate":"2022-10-10T04:05:50","Links":[{"Rel":"self","Href":"/api/api/marketsummary/indexsummary/MNC36","Method":"GET"}]},{"IndexCode":"SMInfra18","PrevVal":333.959,"HighVal":333.959,"LowVal":333.959,"LastVal":333.959,"ChgVal":0,"ChgPct":0,"DtCreate":"2022-10-10T04:05:50","Links":[{"Rel":"self","Href":"/api/api/marketsummary/indexsummary/SMInfra18","Method":"GET"}]},{"IndexCode":"PEFINDO25","PrevVal":287.825,"HighVal":287.825,"LowVal":287.825,"LastVal":287.825,"ChgVal":0,"ChgPct":0,"DtCreate":"2022-10-10T04:05:50","Links":[{"Rel":"self","Href":"/api/api/marketsummary/indexsummary/PEFINDO25","Method":"GET"}]},{"IndexCode":"JII70","PrevVal":207.47,"HighVal":207.47,"LowVal":207.47,"LastVal":207.47,"ChgVal":0,"ChgPct":0,"DtCreate":"2022-10-10T04:05:50","Links":[{"Rel":"self","Href":"/api/api/marketsummary/indexsummary/JII70","Method":"GET"}]},{"IndexCode":"ISSI","PrevVal":205.88,"HighVal":205.88,"LowVal":205.88,"LastVal":205.88,"ChgVal":0,"ChgPct":0,"DtCreate":"2022-10-10T04:05:50","Links":[{"Rel":"self","Href":"/api/api/marketsummary/indexsummary/ISSI","Method":"GET"}]},{"IndexCode":"I-GRADE","PrevVal":201.785,"HighVal":201.785,"LowVal":201.785,"LastVal":201.785,"ChgVal":0,"ChgPct":0,"DtCreate":"2022-10-10T04:05:50","Links":[{"Rel":"self","Href":"/api/api/marketsummary/indexsummary/I-GRADE","Method":"GET"}]},{"IndexCode":"IDXQ30","PrevVal":165.021,"HighVal":165.021,"LowVal":165.021,"LastVal":165.021,"ChgVal":0,"ChgPct":0,"DtCreate":"2022-10-10T04:05:50","Links":[{"Rel":"self","Href":"/api/api/marketsummary/indexsummary/IDXQ30","Method":"GET"}]},{"IndexCode":"IDXV30","PrevVal":158.451,"HighVal":158.451,"LowVal":158.451,"LastVal":158.451,"ChgVal":0,"ChgPct":0,"DtCreate":"2022-10-10T04:05:50","Links":[{"Rel":"self","Href":"/api/api/marketsummary/indexsummary/IDXV30","Method":"GET"}]},{"IndexCode":"IDXESGL","PrevVal":143.73,"HighVal":143.73,"LowVal":143.73,"LastVal":143.73,"ChgVal":0,"ChgPct":0,"DtCreate":"2022-10-10T04:05:50","Links":[{"Rel":"self","Href":"/api/api/marketsummary/indexsummary/IDXESGL","Method":"GET"}]},{"IndexCode":"IDX80","PrevVal":140.769,"HighVal":140.769,"LowVal":140.769,"LastVal":140.769,"ChgVal":0,"ChgPct":0,"DtCreate":"2022-10-10T04:05:50","Links":[{"Rel":"self","Href":"/api/api/marketsummary/indexsummary/IDX80","Method":"GET"}]},{"IndexCode":"ESGSKEHATI","PrevVal":136.108,"HighVal":136.108,"LowVal":136.108,"LastVal":136.108,"ChgVal":0,"ChgPct":0,"DtCreate":"2022-10-10T04:05:50","Links":[{"Rel":"self","Href":"/api/api/marketsummary/indexsummary/ESGSKEHATI","Method":"GET"}]},{"IndexCode":"ESGQKEHATI","PrevVal":135.532,"HighVal":135.532,"LowVal":135.532,"LastVal":135.532,"ChgVal":0,"ChgPct":0,"DtCreate":"2022-10-10T04:05:50","Links":[{"Rel":"self","Href":"/api/api/marketsummary/indexsummary/ESGQKEHATI","Method":"GET"}]},{"IndexCode":"IDXMESBUMN","PrevVal":100.343,"HighVal":100.343,"LowVal":100.343,"LastVal":100.343,"ChgVal":0,"ChgPct":0,"DtCreate":"2022-10-10T04:05:50","Links":[{"Rel":"self","Href":"/api/api/marketsummary/indexsummary/IDXMESBUMN","Method":"GET"}]}]