[{"No":1,"IDRecap":66266,"Date":"2022-10-31T00:00:00","IDInstrument":"ACCEL","NameInstrument":null,"IDBoard":"NG","Volume":10000000,"Value":850000000,"Frequency":1},{"No":2,"IDRecap":66267,"Date":"2022-10-31T00:00:00","IDInstrument":"ACCEL","NameInstrument":null,"IDBoard":"RG","Volume":29227200,"Value":2194572900,"Frequency":3136},{"No":3,"IDRecap":66268,"Date":"2022-10-31T00:00:00","IDInstrument":"ACCEL","NameInstrument":null,"IDBoard":"TN","Volume":0,"Value":0,"Frequency":0},{"No":4,"IDRecap":66269,"Date":"2022-10-31T00:00:00","IDInstrument":"MUTI","NameInstrument":null,"IDBoard":"NG","Volume":0,"Value":0,"Frequency":0},{"No":5,"IDRecap":66270,"Date":"2022-10-31T00:00:00","IDInstrument":"MUTI","NameInstrument":null,"IDBoard":"RG","Volume":478100,"Value":457384000,"Frequency":169},{"No":6,"IDRecap":66271,"Date":"2022-10-31T00:00:00","IDInstrument":"MUTI","NameInstrument":null,"IDBoard":"TN","Volume":0,"Value":0,"Frequency":0},{"No":7,"IDRecap":66272,"Date":"2022-10-31T00:00:00","IDInstrument":"ORDI","NameInstrument":null,"IDBoard":"NG","Volume":1050056808,"Value":1345852061299,"Frequency":798},{"No":8,"IDRecap":66273,"Date":"2022-10-31T00:00:00","IDInstrument":"ORDI","NameInstrument":null,"IDBoard":"RG","Volume":18266593600,"Value":12373575634900,"Frequency":1157458},{"No":9,"IDRecap":66274,"Date":"2022-10-31T00:00:00","IDInstrument":"ORDI","NameInstrument":null,"IDBoard":"TN","Volume":396202400,"Value":300933487500,"Frequency":94},{"No":10,"IDRecap":66275,"Date":"2022-10-31T00:00:00","IDInstrument":"RGHI","NameInstrument":null,"IDBoard":"NG","Volume":418,"Value":751,"Frequency":7},{"No":11,"IDRecap":66276,"Date":"2022-10-31T00:00:00","IDInstrument":"RGHI","NameInstrument":null,"IDBoard":"TN","Volume":194514400,"Value":328234300,"Frequency":1408},{"No":12,"IDRecap":66277,"Date":"2022-10-31T00:00:00","IDInstrument":"S_WARI","NameInstrument":null,"IDBoard":"NG","Volume":0,"Value":0,"Frequency":0},{"No":13,"IDRecap":66278,"Date":"2022-10-31T00:00:00","IDInstrument":"S_WARI","NameInstrument":null,"IDBoard":"RG","Volume":8708300,"Value":2990690000,"Frequency":925},{"No":14,"IDRecap":66279,"Date":"2022-10-31T00:00:00","IDInstrument":"S_WARI","NameInstrument":null,"IDBoard":"TN","Volume":0,"Value":0,"Frequency":0},{"No":15,"IDRecap":66280,"Date":"2022-10-31T00:00:00","IDInstrument":"WARI","NameInstrument":null,"IDBoard":"NG","Volume":14580397,"Value":1603805073,"Frequency":12},{"No":16,"IDRecap":66281,"Date":"2022-10-31T00:00:00","IDInstrument":"WARI","NameInstrument":null,"IDBoard":"RG","Volume":570253000,"Value":20665743000,"Frequency":44596},{"No":17,"IDRecap":66282,"Date":"2022-10-31T00:00:00","IDInstrument":"WARI","NameInstrument":null,"IDBoard":"TN","Volume":0,"Value":0,"Frequency":0},{"No":18,"IDRecap":66283,"Date":"2022-10-31T00:00:00","IDInstrument":"WATCHLIST","NameInstrument":null,"IDBoard":"NG","Volume":533930500,"Value":27653079900,"Frequency":22},{"No":19,"IDRecap":66284,"Date":"2022-10-31T00:00:00","IDInstrument":"WATCHLIST","NameInstrument":null,"IDBoard":"RG","Volume":943893300,"Value":93891551900,"Frequency":36464},{"No":20,"IDRecap":66285,"Date":"2022-10-31T00:00:00","IDInstrument":"WATCHLIST","NameInstrument":null,"IDBoard":"TN","Volume":0,"Value":0,"Frequency":0},{"No":21,"IDRecap":66286,"Date":"2022-10-31T00:00:00","IDInstrument":"ETF","NameInstrument":null,"IDBoard":"RG","Volume":401600,"Value":450469500,"Frequency":131},{"No":22,"IDRecap":66287,"Date":"2022-10-31T00:00:00","IDInstrument":"DIRE","NameInstrument":null,"IDBoard":"NG","Volume":0,"Value":0,"Frequency":0},{"No":23,"IDRecap":66288,"Date":"2022-10-31T00:00:00","IDInstrument":"DINFRA","NameInstrument":null,"IDBoard":"RG","Volume":0,"Value":0,"Frequency":0},{"No":24,"IDRecap":66289,"Date":"2022-10-31T00:00:00","IDInstrument":"ETF","NameInstrument":null,"IDBoard":"TN","Volume":0,"Value":0,"Frequency":0},{"No":25,"IDRecap":66290,"Date":"2022-10-31T00:00:00","IDInstrument":"ETF","NameInstrument":null,"IDBoard":"NG","Volume":0,"Value":0,"Frequency":0},{"No":26,"IDRecap":66291,"Date":"2022-10-31T00:00:00","IDInstrument":"DIRE","NameInstrument":null,"IDBoard":"TN","Volume":0,"Value":0,"Frequency":0},{"No":27,"IDRecap":66292,"Date":"2022-10-31T00:00:00","IDInstrument":"DIRE","NameInstrument":null,"IDBoard":"RG","Volume":76500,"Value":6914500,"Frequency":38},{"No":28,"IDRecap":66293,"Date":"2022-10-31T00:00:00","IDInstrument":"DINFRA","NameInstrument":null,"IDBoard":"NG","Volume":0,"Value":0,"Frequency":0},{"No":29,"IDRecap":66294,"Date":"2022-10-31T00:00:00","IDInstrument":"DINFRA","NameInstrument":null,"IDBoard":"TN","Volume":0,"Value":0,"Frequency":0}]